freshrelease_mcp/__init__.py
freshrelease_mcp/server.py
freshrelease_mcp-1.12.0.dist-info/METADATA
freshrelease_mcp-1.12.0.dist-info/WHEEL
freshrelease_mcp-1.12.0.dist-info/entry_points.txt
freshrelease_mcp-1.12.0.dist-info/licenses/LICENSE
freshrelease_mcp-1.12.0.dist-info/RECORD
