Metadata-Version: 2.4
Name: freshrelease-mcp
Version: 1.12.0
Summary: An MCP server for Freshrelease - enables Cursor AI to interact with Freshrelease projects
Author-email: Kalidass mani <kalidass.mani@freshworks.com>
License-File: LICENSE
Keywords: ai,assistant,cursor,freshrelease,mcp
Classifier: Development Status :: 4 - Beta
Classifier: Intended Audience :: Developers
Classifier: License :: OSI Approved :: MIT License
Classifier: Programming Language :: Python :: 3
Classifier: Programming Language :: Python :: 3.10
Classifier: Programming Language :: Python :: 3.11
Classifier: Programming Language :: Python :: 3.12
Classifier: Topic :: Software Development :: Libraries :: Python Modules
Requires-Python: >=3.10
Requires-Dist: httpx>=0.28.1
Requires-Dist: mcp>=1.3.0
Requires-Dist: pydantic>=2.10.6
